fuku/__init__.py
fuku/__init__.py~
fuku/app.py
fuku/client.py
fuku/cluster.py
fuku/configuration.py
fuku/container.py
fuku/datadog.py
fuku/db.py
fuku/delivery.py
fuku/image.py
fuku/machine.py
fuku/metrics.py
fuku/module.py
fuku/node.py
fuku/papertrail.py
fuku/pg.py
fuku/profile.py
fuku/redis.py
fuku/region.py
fuku/route.py
fuku/runner.py
fuku/service.py
fuku/session.py
fuku/ssl.py
fuku/task.py
fuku/utils.py
fuku/scripts/fuku
fuku/scripts/data/arch-user-data.sh
fuku/scripts/data/ec2-policy.json
fuku/scripts/data/ecs-assume-role.json
fuku/scripts/data/machine.json
fuku/scripts/data/s3-policy.json
fuku-0.0.33.data/scripts/fuku
fuku-0.0.33.dist-info/METADATA
fuku-0.0.33.dist-info/RECORD
fuku-0.0.33.dist-info/WHEEL
fuku-0.0.33.dist-info/top_level.txt
