Metadata-Version: 2.1
Name: fuku
Version: 0.0.33
Summary: Easier Docker based deployments to AWS.
Home-page: https://github.com/uptick/python-fuku
Author: Luke Hodkinson
Author-email: luke.hodkinson@uptickhq.com
Maintainer: Uptick
Maintainer-email: dev@uptickhq.com
License: BSD
Platform: UNKNOWN
Classifier: Development Status :: 3 - Alpha
Classifier: Intended Audience :: Developers
Classifier: License :: OSI Approved :: BSD License
Classifier: Natural Language :: English
Classifier: Operating System :: OS Independent
Classifier: Programming Language :: Python
Classifier: Programming Language :: Python :: 2
Classifier: Programming Language :: Python :: 2.7
Classifier: Programming Language :: Python :: 3
Classifier: Programming Language :: Python :: 3.3
Classifier: Programming Language :: Python :: 3.4
Classifier: Programming Language :: Python :: 3.5
Requires-Dist: setuptools
Requires-Dist: six
Requires-Dist: boto3
Requires-Dist: fabric3
Requires-Dist: colorama
Requires-Dist: pprint
